{
    "name": "Long Arms",
    "type": "ability",
    "img": "icons/creatures/eyes/human-single-blue.webp",
    "system": {
        "description": {
            "value": "<p>Add 5 feet to the reach of your melee attacks, as well as when determining your reach for melee opportunity attacks.</p>",
            "chat": "",
            "unidentified": ""
        },
        "source": "Core Rules",
        "type": {
            "value": "race",
            "subtype": "core"
        }
    },
    "effects": [],
    "folder": null,
    "sort": 0,
    "ownership": {
        "default": 0
    },
    "flags": {},
    "_id": "EPAB9QGGCW5C01RX"
}